{
  "$schema": "https://ui.shadcn.com/schema/registry.json",
  "name": "svelte-bits",
  "homepage": "https://sveltebits.xyz",
  "items": [
    {
      "name": "animated-content",
      "type": "registry:component",
      "title": "Animated Content",
      "description": "Scroll-triggered entrance animation with distance, direction, scale and opacity controls. Powered by GSAP + ScrollTrigger.",
      "categories": [
        "animations"
      ],
      "files": [
        {
          "path": "AnimatedContent.svelte",
          "type": "registry:component",
          "target": "$lib/components/svelte-bits/AnimatedContent.svelte"
        }
      ]
    },
    {
      "name": "fade-content",
      "type": "registry:component",
      "title": "Fade Content",
      "description": "Scroll-triggered fade-in (with optional blur) entrance using GSAP + ScrollTrigger, with optional auto-disappearance.",
      "categories": [
        "animations"
      ],
      "files": [
        {
          "path": "FadeContent.svelte",
          "type": "registry:component",
          "target": "$lib/components/svelte-bits/FadeContent.svelte"
        }
      ]
    },
    {
      "name": "magic-rings",
      "type": "registry:component",
      "title": "Magic Rings",
      "description": "WebGL2 concentric ring animation with mouse parallax, hover scale, and click burst. Real three.js shader.",
      "categories": [
        "animations"
      ],
      "files": [
        {
          "path": "MagicRings.svelte",
          "type": "registry:component",
          "target": "$lib/components/svelte-bits/MagicRings.svelte"
        }
      ]
    },
    {
      "name": "noise",
      "type": "registry:component",
      "title": "Noise",
      "description": "Full-viewport animated film-grain canvas overlay.",
      "categories": [
        "animations"
      ],
      "files": [
        {
          "path": "Noise.svelte",
          "type": "registry:component",
          "target": "$lib/components/svelte-bits/Noise.svelte"
        }
      ]
    },
    {
      "name": "splash-cursor",
      "type": "registry:component",
      "title": "Splash Cursor",
      "description": "Liquid splash burst at cursor with curling ripples and waves.",
      "categories": [
        "animations"
      ],
      "files": [
        {
          "path": "SplashCursor.svelte",
          "type": "registry:component",
          "target": "$lib/components/svelte-bits/SplashCursor.svelte"
        }
      ]
    },
    {
      "name": "star-border",
      "type": "registry:component",
      "title": "Star Border",
      "description": "Button-like wrapper with two animated radial-gradient sweeps tracing the top and bottom border.",
      "categories": [
        "animations"
      ],
      "files": [
        {
          "path": "StarBorder.svelte",
          "type": "registry:component",
          "target": "$lib/components/svelte-bits/StarBorder.svelte"
        }
      ]
    },
    {
      "name": "aurora",
      "type": "registry:component",
      "title": "Aurora",
      "description": "WebGL aurora background with configurable color stops, amplitude, blend and speed. Real OGL shader, not a CSS gradient.",
      "categories": [
        "backgrounds"
      ],
      "files": [
        {
          "path": "Aurora.svelte",
          "type": "registry:component",
          "target": "$lib/components/svelte-bits/Aurora.svelte"
        }
      ]
    },
    {
      "name": "balatro",
      "type": "registry:component",
      "title": "Balatro",
      "description": "Swirling pixel-painted Balatro-style WebGL background with mouse interaction.",
      "categories": [
        "backgrounds"
      ],
      "files": [
        {
          "path": "Balatro.svelte",
          "type": "registry:component",
          "target": "$lib/components/svelte-bits/Balatro.svelte"
        }
      ]
    },
    {
      "name": "color-bends",
      "type": "registry:component",
      "title": "Color Bends",
      "description": "Three.js shader background with warped color bands, pointer parallax, noise, and rotation controls.",
      "categories": [
        "backgrounds"
      ],
      "files": [
        {
          "path": "ColorBends.svelte",
          "type": "registry:component",
          "target": "$lib/components/svelte-bits/ColorBends.svelte"
        }
      ]
    },
    {
      "name": "dark-veil",
      "type": "registry:component",
      "title": "Dark Veil",
      "description": "Dark veil WebGL background with hue shift, scanlines, noise and warp controls.",
      "categories": [
        "backgrounds"
      ],
      "files": [
        {
          "path": "DarkVeil.svelte",
          "type": "registry:component",
          "target": "$lib/components/svelte-bits/DarkVeil.svelte"
        }
      ]
    },
    {
      "name": "dither",
      "type": "registry:component",
      "title": "Dither",
      "description": "Bayer-dithered animated wave field.",
      "categories": [
        "backgrounds"
      ],
      "files": [
        {
          "path": "Dither.svelte",
          "type": "registry:component",
          "target": "$lib/components/svelte-bits/Dither.svelte"
        }
      ]
    },
    {
      "name": "dot-field",
      "type": "registry:component",
      "title": "Dot Field",
      "description": "Interactive dotted canvas background with cursor bulge, glow, sparkle, and wave controls.",
      "categories": [
        "backgrounds"
      ],
      "files": [
        {
          "path": "DotField.svelte",
          "type": "registry:component",
          "target": "$lib/components/svelte-bits/DotField.svelte"
        }
      ]
    },
    {
      "name": "dot-grid",
      "type": "registry:component",
      "title": "Dot Grid",
      "description": "Interactive grid of dots with cursor proximity highlighting and shockwave click physics.",
      "categories": [
        "backgrounds"
      ],
      "files": [
        {
          "path": "DotGrid.svelte",
          "type": "registry:component",
          "target": "$lib/components/svelte-bits/DotGrid.svelte"
        }
      ]
    },
    {
      "name": "evil-eye",
      "type": "registry:component",
      "title": "Evil Eye",
      "description": "Reactive evil eye background with cursor-tracked pupil.",
      "categories": [
        "backgrounds"
      ],
      "files": [
        {
          "path": "EvilEye.svelte",
          "type": "registry:component",
          "target": "$lib/components/svelte-bits/EvilEye.svelte"
        }
      ]
    },
    {
      "name": "faulty-terminal",
      "type": "registry:component",
      "title": "Faulty Terminal",
      "description": "OGL terminal-style shader background with scanlines, glitches, curvature, mouse reaction, and load animation.",
      "categories": [
        "backgrounds"
      ],
      "files": [
        {
          "path": "FaultyTerminal.svelte",
          "type": "registry:component",
          "target": "$lib/components/svelte-bits/FaultyTerminal.svelte"
        }
      ]
    },
    {
      "name": "floating-lines",
      "type": "registry:component",
      "title": "Floating Lines",
      "description": "Layered animated wave lines with parallax & bend.",
      "categories": [
        "backgrounds"
      ],
      "files": [
        {
          "path": "FloatingLines.svelte",
          "type": "registry:component",
          "target": "$lib/components/svelte-bits/FloatingLines.svelte"
        }
      ]
    },
    {
      "name": "galaxy",
      "type": "registry:component",
      "title": "Galaxy",
      "description": "Animated galaxy of twinkling stars.",
      "categories": [
        "backgrounds"
      ],
      "files": [
        {
          "path": "Galaxy.svelte",
          "type": "registry:component",
          "target": "$lib/components/svelte-bits/Galaxy.svelte"
        }
      ]
    },
    {
      "name": "gradient-blinds",
      "type": "registry:component",
      "title": "Gradient Blinds",
      "description": "Animated gradient blinds with spotlight tracking.",
      "categories": [
        "backgrounds"
      ],
      "files": [
        {
          "path": "GradientBlinds.svelte",
          "type": "registry:component",
          "target": "$lib/components/svelte-bits/GradientBlinds.svelte"
        }
      ]
    },
    {
      "name": "grainient",
      "type": "registry:component",
      "title": "Grainient",
      "description": "Animated WebGL2 grainy gradient.",
      "categories": [
        "backgrounds"
      ],
      "files": [
        {
          "path": "Grainient.svelte",
          "type": "registry:component",
          "target": "$lib/components/svelte-bits/Grainient.svelte"
        }
      ]
    },
    {
      "name": "grid-distortion",
      "type": "registry:component",
      "title": "Grid Distortion",
      "description": "Image grid distortion driven by mouse movement.",
      "categories": [
        "backgrounds"
      ],
      "files": [
        {
          "path": "GridDistortion.svelte",
          "type": "registry:component",
          "target": "$lib/components/svelte-bits/GridDistortion.svelte"
        }
      ]
    },
    {
      "name": "grid-motion",
      "type": "registry:component",
      "title": "Grid Motion",
      "description": "Grid that pans with mouse position, powered by GSAP.",
      "categories": [
        "backgrounds"
      ],
      "files": [
        {
          "path": "GridMotion.svelte",
          "type": "registry:component",
          "target": "$lib/components/svelte-bits/GridMotion.svelte"
        }
      ]
    },
    {
      "name": "hyperspeed",
      "type": "registry:component",
      "title": "Hyperspeed",
      "description": "Three.js hyperspeed road background with bloom, SMAA, distortion presets, animated light trails, and hold-to-accelerate interaction.",
      "categories": [
        "backgrounds"
      ],
      "files": [
        {
          "path": "Hyperspeed.svelte",
          "type": "registry:component",
          "target": "$lib/components/svelte-bits/Hyperspeed.svelte"
        }
      ]
    },
    {
      "name": "iridescence",
      "type": "registry:component",
      "title": "Iridescence",
      "description": "Animated iridescent WebGL background with optional mouse parallax.",
      "categories": [
        "backgrounds"
      ],
      "files": [
        {
          "path": "Iridescence.svelte",
          "type": "registry:component",
          "target": "$lib/components/svelte-bits/Iridescence.svelte"
        }
      ]
    },
    {
      "name": "letter-glitch",
      "type": "registry:component",
      "title": "Letter Glitch",
      "description": "Cascading glitchy letter grid background.",
      "categories": [
        "backgrounds"
      ],
      "files": [
        {
          "path": "LetterGlitch.svelte",
          "type": "registry:component",
          "target": "$lib/components/svelte-bits/LetterGlitch.svelte"
        }
      ]
    },
    {
      "name": "light-pillar",
      "type": "registry:component",
      "title": "LightPillar",
      "description": "Volumetric raymarched light pillar.",
      "categories": [
        "backgrounds"
      ],
      "files": [
        {
          "path": "LightPillar.svelte",
          "type": "registry:component",
          "target": "$lib/components/svelte-bits/LightPillar.svelte"
        }
      ]
    },
    {
      "name": "light-rays",
      "type": "registry:component",
      "title": "Light Rays",
      "description": "Animated volumetric light rays rendered with OGL.",
      "categories": [
        "backgrounds"
      ],
      "files": [
        {
          "path": "LightRays.svelte",
          "type": "registry:component",
          "target": "$lib/components/svelte-bits/LightRays.svelte"
        }
      ]
    },
    {
      "name": "lightning",
      "type": "registry:component",
      "title": "Lightning",
      "description": "Procedural lightning bolt WebGL background.",
      "categories": [
        "backgrounds"
      ],
      "files": [
        {
          "path": "Lightning.svelte",
          "type": "registry:component",
          "target": "$lib/components/svelte-bits/Lightning.svelte"
        }
      ]
    },
    {
      "name": "line-waves",
      "type": "registry:component",
      "title": "Line Waves",
      "description": "Warped line waves background powered by OGL.",
      "categories": [
        "backgrounds"
      ],
      "files": [
        {
          "path": "LineWaves.svelte",
          "type": "registry:component",
          "target": "$lib/components/svelte-bits/LineWaves.svelte"
        }
      ]
    },
    {
      "name": "liquid-chrome",
      "type": "registry:component",
      "title": "Liquid Chrome",
      "description": "Liquid chrome animated WebGL background with mouse and touch interaction.",
      "categories": [
        "backgrounds"
      ],
      "files": [
        {
          "path": "LiquidChrome.svelte",
          "type": "registry:component",
          "target": "$lib/components/svelte-bits/LiquidChrome.svelte"
        }
      ]
    },
    {
      "name": "liquid-ether",
      "type": "registry:component",
      "title": "Liquid Ether",
      "description": "Interactive liquid shader with flowing distortion and customizable colors.",
      "categories": [
        "backgrounds"
      ],
      "files": [
        {
          "path": "LiquidEther.svelte",
          "type": "registry:component",
          "target": "$lib/components/svelte-bits/LiquidEther.svelte"
        }
      ]
    },
    {
      "name": "orb",
      "type": "registry:component",
      "title": "Orb",
      "description": "Dreamy hue-shifting orb with hover interaction.",
      "categories": [
        "backgrounds"
      ],
      "files": [
        {
          "path": "Orb.svelte",
          "type": "registry:component",
          "target": "$lib/components/svelte-bits/Orb.svelte"
        }
      ]
    },
    {
      "name": "particles",
      "type": "registry:component",
      "title": "Particles",
      "description": "OGL-based 3D point cloud particles with hover interaction.",
      "categories": [
        "backgrounds"
      ],
      "files": [
        {
          "path": "Particles.svelte",
          "type": "registry:component",
          "target": "$lib/components/svelte-bits/Particles.svelte"
        }
      ]
    },
    {
      "name": "pixel-blast",
      "type": "registry:component",
      "title": "PixelBlast",
      "description": "Pixelated dithered shape field with ripples and liquid distortion.",
      "categories": [
        "backgrounds"
      ],
      "files": [
        {
          "path": "PixelBlast.svelte",
          "type": "registry:component",
          "target": "$lib/components/svelte-bits/PixelBlast.svelte"
        }
      ]
    },
    {
      "name": "pixel-snow",
      "type": "registry:component",
      "title": "Pixel Snow",
      "description": "Volumetric pixel snowfall background.",
      "categories": [
        "backgrounds"
      ],
      "files": [
        {
          "path": "PixelSnow.svelte",
          "type": "registry:component",
          "target": "$lib/components/svelte-bits/PixelSnow.svelte"
        }
      ]
    },
    {
      "name": "plasma",
      "type": "registry:component",
      "title": "Plasma",
      "description": "Volumetric plasma WebGL2 background with optional mouse interaction and color tinting.",
      "categories": [
        "backgrounds"
      ],
      "files": [
        {
          "path": "Plasma.svelte",
          "type": "registry:component",
          "target": "$lib/components/svelte-bits/Plasma.svelte"
        }
      ]
    },
    {
      "name": "plasma-wave",
      "type": "registry:component",
      "title": "Plasma Wave",
      "description": "Raymarched plasma wave background.",
      "categories": [
        "backgrounds"
      ],
      "files": [
        {
          "path": "PlasmaWave.svelte",
          "type": "registry:component",
          "target": "$lib/components/svelte-bits/PlasmaWave.svelte"
        }
      ]
    },
    {
      "name": "prism",
      "type": "registry:component",
      "title": "Prism",
      "description": "Animated raymarched prism with hue and bloom.",
      "categories": [
        "backgrounds"
      ],
      "files": [
        {
          "path": "Prism.svelte",
          "type": "registry:component",
          "target": "$lib/components/svelte-bits/Prism.svelte"
        }
      ]
    },
    {
      "name": "prismatic-burst",
      "type": "registry:component",
      "title": "PrismaticBurst",
      "description": "Volumetric ray burst with bend and color gradient.",
      "categories": [
        "backgrounds"
      ],
      "files": [
        {
          "path": "PrismaticBurst.svelte",
          "type": "registry:component",
          "target": "$lib/components/svelte-bits/PrismaticBurst.svelte"
        }
      ]
    },
    {
      "name": "radar",
      "type": "registry:component",
      "title": "Radar",
      "description": "Radar sweep background rendered with OGL.",
      "categories": [
        "backgrounds"
      ],
      "files": [
        {
          "path": "Radar.svelte",
          "type": "registry:component",
          "target": "$lib/components/svelte-bits/Radar.svelte"
        }
      ]
    },
    {
      "name": "ripple-grid",
      "type": "registry:component",
      "title": "Ripple Grid",
      "description": "Animated rippling grid background powered by OGL with mouse interaction.",
      "categories": [
        "backgrounds"
      ],
      "files": [
        {
          "path": "RippleGrid.svelte",
          "type": "registry:component",
          "target": "$lib/components/svelte-bits/RippleGrid.svelte"
        }
      ]
    },
    {
      "name": "shape-grid",
      "type": "registry:component",
      "title": "Shape Grid",
      "description": "Animated grid of squares, hexagons, circles, or triangles with hover trail and configurable scroll direction.",
      "categories": [
        "backgrounds"
      ],
      "files": [
        {
          "path": "ShapeGrid.svelte",
          "type": "registry:component",
          "target": "$lib/components/svelte-bits/ShapeGrid.svelte"
        }
      ]
    },
    {
      "name": "silk",
      "type": "registry:component",
      "title": "Silk",
      "description": "Silk-like animated WebGL background using a Three.js shader plane.",
      "categories": [
        "backgrounds"
      ],
      "files": [
        {
          "path": "Silk.svelte",
          "type": "registry:component",
          "target": "$lib/components/svelte-bits/Silk.svelte"
        }
      ]
    },
    {
      "name": "soft-aurora",
      "type": "registry:component",
      "title": "Soft Aurora",
      "description": "Soft aurora bands rendered with OGL using Perlin noise.",
      "categories": [
        "backgrounds"
      ],
      "files": [
        {
          "path": "SoftAurora.svelte",
          "type": "registry:component",
          "target": "$lib/components/svelte-bits/SoftAurora.svelte"
        }
      ]
    },
    {
      "name": "threads",
      "type": "registry:component",
      "title": "Threads",
      "description": "Animated WebGL line/threads background with mouse parallax.",
      "categories": [
        "backgrounds"
      ],
      "files": [
        {
          "path": "Threads.svelte",
          "type": "registry:component",
          "target": "$lib/components/svelte-bits/Threads.svelte"
        }
      ]
    },
    {
      "name": "waves",
      "type": "registry:component",
      "title": "Waves",
      "description": "Perlin-noise wavy line grid that reacts to the cursor.",
      "categories": [
        "backgrounds"
      ],
      "files": [
        {
          "path": "Waves.svelte",
          "type": "registry:component",
          "target": "$lib/components/svelte-bits/Waves.svelte"
        }
      ]
    },
    {
      "name": "dock",
      "type": "registry:component",
      "title": "Dock",
      "description": "macOS-style magnification dock with spring physics. Each item scales smoothly based on cursor distance.",
      "categories": [
        "components"
      ],
      "files": [
        {
          "path": "Dock.svelte",
          "type": "registry:component",
          "target": "$lib/components/svelte-bits/Dock.svelte"
        }
      ]
    },
    {
      "name": "flying-posters",
      "type": "registry:component",
      "title": "Flying Posters",
      "description": "3D posters rotate on scroll infinitely.",
      "categories": [
        "components"
      ],
      "files": [
        {
          "path": "FlyingPosters.svelte",
          "type": "registry:component",
          "target": "$lib/components/svelte-bits/FlyingPosters.svelte"
        }
      ]
    },
    {
      "name": "blur-text",
      "type": "registry:component",
      "title": "Blur Text",
      "description": "Per-word/letter blur-in animation triggered when scrolled into view, with configurable direction, easing and stepped keyframes.",
      "categories": [
        "text-animations"
      ],
      "files": [
        {
          "path": "BlurText.svelte",
          "type": "registry:component",
          "target": "$lib/components/svelte-bits/BlurText.svelte"
        }
      ]
    },
    {
      "name": "count-up",
      "type": "registry:component",
      "title": "Count Up",
      "description": "Spring-animated number counter that counts up (or down) when scrolled into view, with configurable spring physics, delay, and number formatting.",
      "categories": [
        "text-animations"
      ],
      "files": [
        {
          "path": "CountUp.svelte",
          "type": "registry:component",
          "target": "$lib/components/svelte-bits/CountUp.svelte"
        }
      ]
    },
    {
      "name": "falling-text",
      "type": "registry:component",
      "title": "Falling Text",
      "description": "Characters fall with gravity + bounce creating a playful entrance.",
      "categories": [
        "text-animations"
      ],
      "files": [
        {
          "path": "FallingText.svelte",
          "type": "registry:component",
          "target": "$lib/components/svelte-bits/FallingText.svelte"
        }
      ]
    },
    {
      "name": "glitch-text",
      "type": "registry:component",
      "title": "Glitch Text",
      "description": "RGB-split glitch effect on text using clip-path keyframe animation, with optional hover-only mode.",
      "categories": [
        "text-animations"
      ],
      "files": [
        {
          "path": "GlitchText.svelte",
          "type": "registry:component",
          "target": "$lib/components/svelte-bits/GlitchText.svelte"
        }
      ]
    },
    {
      "name": "gradient-text",
      "type": "registry:component",
      "title": "Gradient Text",
      "description": "Animated multi-color gradient text with optional border, direction, yoyo and pause-on-hover.",
      "categories": [
        "text-animations"
      ],
      "files": [
        {
          "path": "GradientText.svelte",
          "type": "registry:component",
          "target": "$lib/components/svelte-bits/GradientText.svelte"
        }
      ]
    },
    {
      "name": "shiny-text",
      "type": "registry:component",
      "title": "Shiny Text",
      "description": "Animated shiny gradient sweep across text, with yoyo + direction controls.",
      "categories": [
        "text-animations"
      ],
      "files": [
        {
          "path": "ShinyText.svelte",
          "type": "registry:component",
          "target": "$lib/components/svelte-bits/ShinyText.svelte"
        }
      ]
    },
    {
      "name": "split-text",
      "type": "registry:component",
      "title": "Split Text",
      "description": "Splits text into characters / words for staggered entrance animation.",
      "categories": [
        "text-animations"
      ],
      "files": [
        {
          "path": "SplitText.svelte",
          "type": "registry:component",
          "target": "$lib/components/svelte-bits/SplitText.svelte"
        }
      ]
    },
    {
      "name": "true-focus",
      "type": "registry:component",
      "title": "True Focus",
      "description": "Applies dynamic blur / clarity based over a series of words in order.",
      "categories": [
        "text-animations"
      ],
      "files": [
        {
          "path": "TrueFocus.svelte",
          "type": "registry:component",
          "target": "$lib/components/svelte-bits/TrueFocus.svelte"
        }
      ]
    }
  ]
}
